apiutils/__init__.py
apiutils/cache.py
apiutils/constants.py
apiutils/middleware.py
apiutils/parsers.py
apiutils/renderers.py
apiutils/sms.py
apiutils/storages.py
apiutils/utils.py
apiutils/verify_code.py
apiutils/templates/error.html
apiutils/templates/apiutils/api_doc.md
apiutils/templates/apiutils/api_info.js
apiutils/templates/import_export/change_list.html
apiutils/templates/import_export/ex_import.html
apiutils-1.0.12.dist-info/LICENSE
apiutils-1.0.12.dist-info/METADATA
apiutils-1.0.12.dist-info/WHEEL
apiutils-1.0.12.dist-info/top_level.txt
apiutils-1.0.12.dist-info/RECORD
