Metadata-Version: 2.1
Name: apiutils
Version: 1.0.12
Summary: apiutils
Home-page: https://github.com/007gzs/apiutils
Author: 007gzs
Author-email: 007gzs@gmail.com
License: LGPL v3
Keywords: apiutils utils
Platform: UNKNOWN
Classifier: Development Status :: 3 - Alpha
Classifier: Intended Audience :: Developers
Classifier: Topic :: Software Development :: Build Tools
Classifier: License :: OSI Approved :: GNU Lesser General Public License v3 (LGPLv3)
Classifier: Programming Language :: Python :: 3
Classifier: Programming Language :: Python :: 3.4
Classifier: Programming Language :: Python :: 3.5
Classifier: Programming Language :: Python :: 3.6
Classifier: Programming Language :: Python :: 3.7
Classifier: Programming Language :: Python :: 3.8
Requires-Dist: django-constance
Requires-Dist: aliyun-python-sdk-core
Requires-Dist: django-restframework-apiview
